ntdgotv_langtools/__init__.py
ntdgotv_langtools/main.py
ntdgotv_langtools-0.2.1.dist-info/METADATA
ntdgotv_langtools-0.2.1.dist-info/WHEEL
ntdgotv_langtools-0.2.1.dist-info/top_level.txt
ntdgotv_langtools-0.2.1.dist-info/RECORD
