Metadata-Version: 2.1
Name: ntdgotv_langtools
Version: 0.2.1
Summary: # ntdGoTV_langtools
Author: ntdGoTV
Author-email: ntdGoTV@gmail.com
Provides-Extra: dev
Requires-Dist: asttokens ==2.4.1 ; extra == 'dev'
Requires-Dist: attrs ==23.2.0 ; extra == 'dev'
Requires-Dist: backcall ==0.2.0 ; extra == 'dev'
Requires-Dist: beautifulsoup4 ==4.12.3 ; extra == 'dev'
Requires-Dist: bleach ==6.1.0 ; extra == 'dev'
Requires-Dist: certifi ==2024.2.2 ; extra == 'dev'
Requires-Dist: charset-normalizer ==3.3.2 ; extra == 'dev'
Requires-Dist: colorama ==0.4.6 ; extra == 'dev'
Requires-Dist: decorator ==5.1.1 ; extra == 'dev'
Requires-Dist: defusedxml ==0.7.1 ; extra == 'dev'
Requires-Dist: docopt ==0.6.2 ; extra == 'dev'
Requires-Dist: docutils ==0.21.2 ; extra == 'dev'
Requires-Dist: executing ==2.0.1 ; extra == 'dev'
Requires-Dist: fastjsonschema ==2.19.1 ; extra == 'dev'
Requires-Dist: idna ==3.7 ; extra == 'dev'
Requires-Dist: importlib-metadata ==7.1.0 ; extra == 'dev'
Requires-Dist: ipython ==8.12.3 ; extra == 'dev'
Requires-Dist: jaraco.classes ==3.4.0 ; extra == 'dev'
Requires-Dist: jaraco.context ==5.3.0 ; extra == 'dev'
Requires-Dist: jaraco.functools ==4.0.1 ; extra == 'dev'
Requires-Dist: jedi ==0.19.1 ; extra == 'dev'
Requires-Dist: Jinja2 ==3.1.4 ; extra == 'dev'
Requires-Dist: jsonschema ==4.22.0 ; extra == 'dev'
Requires-Dist: jsonschema-specifications ==2023.12.1 ; extra == 'dev'
Requires-Dist: jupyter-client ==8.6.1 ; extra == 'dev'
Requires-Dist: jupyter-core ==5.7.2 ; extra == 'dev'
Requires-Dist: jupyterlab-pygments ==0.3.0 ; extra == 'dev'
Requires-Dist: keyring ==25.2.1 ; extra == 'dev'
Requires-Dist: markdown-it-py ==3.0.0 ; extra == 'dev'
Requires-Dist: MarkupSafe ==2.1.5 ; extra == 'dev'
Requires-Dist: matplotlib-inline ==0.1.7 ; extra == 'dev'
Requires-Dist: mdurl ==0.1.2 ; extra == 'dev'
Requires-Dist: mistune ==3.0.2 ; extra == 'dev'
Requires-Dist: more-itertools ==10.2.0 ; extra == 'dev'
Requires-Dist: nbclient ==0.10.0 ; extra == 'dev'
Requires-Dist: nbconvert ==7.16.4 ; extra == 'dev'
Requires-Dist: nbformat ==5.10.4 ; extra == 'dev'
Requires-Dist: nh3 ==0.2.17 ; extra == 'dev'
Requires-Dist: packaging ==24.0 ; extra == 'dev'
Requires-Dist: pandocfilters ==1.5.1 ; extra == 'dev'
Requires-Dist: parso ==0.8.4 ; extra == 'dev'
Requires-Dist: pickleshare ==0.7.5 ; extra == 'dev'
Requires-Dist: pipreqs ==0.5.0 ; extra == 'dev'
Requires-Dist: pkginfo ==1.10.0 ; extra == 'dev'
Requires-Dist: platformdirs ==4.2.2 ; extra == 'dev'
Requires-Dist: prompt-toolkit ==3.0.43 ; extra == 'dev'
Requires-Dist: pure-eval ==0.2.2 ; extra == 'dev'
Requires-Dist: Pygments ==2.18.0 ; extra == 'dev'
Requires-Dist: python-dateutil ==2.9.0.post0 ; extra == 'dev'
Requires-Dist: pywin32 ==306 ; extra == 'dev'
Requires-Dist: pywin32-ctypes ==0.2.2 ; extra == 'dev'
Requires-Dist: pyzmq ==26.0.3 ; extra == 'dev'
Requires-Dist: readme-renderer ==43.0 ; extra == 'dev'
Requires-Dist: referencing ==0.35.1 ; extra == 'dev'
Requires-Dist: requests ==2.31.0 ; extra == 'dev'
Requires-Dist: requests-toolbelt ==1.0.0 ; extra == 'dev'
Requires-Dist: rfc3986 ==2.0.0 ; extra == 'dev'
Requires-Dist: rich ==13.7.1 ; extra == 'dev'
Requires-Dist: rpds-py ==0.18.1 ; extra == 'dev'
Requires-Dist: setuptools ==69.5.1 ; extra == 'dev'
Requires-Dist: six ==1.16.0 ; extra == 'dev'
Requires-Dist: soupsieve ==2.5 ; extra == 'dev'
Requires-Dist: stack-data ==0.6.3 ; extra == 'dev'
Requires-Dist: tinycss2 ==1.3.0 ; extra == 'dev'
Requires-Dist: tornado ==6.4 ; extra == 'dev'
Requires-Dist: traitlets ==5.14.3 ; extra == 'dev'
Requires-Dist: twine ==5.1.0 ; extra == 'dev'
Requires-Dist: urllib3 ==2.2.1 ; extra == 'dev'
Requires-Dist: wcwidth ==0.2.13 ; extra == 'dev'
Requires-Dist: webencodings ==0.5.1 ; extra == 'dev'
Requires-Dist: wheel ==0.43.0 ; extra == 'dev'
Requires-Dist: yarg ==0.1.9 ; extra == 'dev'
Requires-Dist: zipp ==3.18.2 ; extra == 'dev'
